README.rst
setup.cfg
setup.py
tox.ini
allure_pytest_bdd_temp.egg-info/PKG-INFO
allure_pytest_bdd_temp.egg-info/SOURCES.txt
allure_pytest_bdd_temp.egg-info/dependency_links.txt
allure_pytest_bdd_temp.egg-info/entry_points.txt
allure_pytest_bdd_temp.egg-info/requires.txt
allure_pytest_bdd_temp.egg-info/top_level.txt
features/background.feature
features/outline.feature
features/scenario.feature
src/__init__.py
src/plugin.py
src/pytest_bdd_listener.py
src/utils.py
test/__init__.py
test/conftest.py
test/outline_test.py
test/scenario_test.py
test/steps.py